README.rst
setup.py
requests_ftp/__init__.py
requests_ftp/ftp.py
requests_ftp.egg-info/PKG-INFO
requests_ftp.egg-info/SOURCES.txt
requests_ftp.egg-info/dependency_links.txt
requests_ftp.egg-info/requires.txt
requests_ftp.egg-info/top_level.txt