Metadata-Version: 1.1
Name: requests-ftp
Version: 0.2.0
Summary: FTP Transport Adapter for Requests.
Home-page: http://github.com/Lukasa/requests_ftp
Author: Cory Benfield
Author-email: cory@lukasa.co.uk
License: Apache 2.0
Platform: UNKNOWN
Classifier: Development Status :: 4 - Beta
Classifier: Intended Audience :: Developers
Classifier: Natural Language :: English
Classifier: License :: OSI Approved :: Apache Software License
Classifier: Programming Language :: Python
Classifier: Programming Language :: Python :: 2.7
